hws/5/adder_1.sv
/* 
    a 1 bit adder that we can daisy chain ripple carry adders
*/

module adder_1(a, b, c_in, sum, c_out);

    input wire a, b, c_in;
    output logic sum, c_out;

    always_comb begin : adder_gates
        c_out = (~c_in & a & b) |
                (c_in & ~a & b) |
                (c_in & a & b) |
                (c_in & a & ~b);
        
        sum = (~c_in & (a ^ b)) |
              (c_in & (a ~^ b));
    end

endmodule

01_game_of_life/adder_n.sv
module adder_n(a, b, c_in, sum, c_out);

parameter N = 2;

input  wire [N-1:0] a, b;
input wire c_in;
output logic [N-1:0] sum;
output logic c_out;


logic [N:0] carries;
always_comb carries[0] = c_in;
always_comb c_out = carries[N];
generate
  genvar i;
  for(i = 0; i < N; i++) begin : ripple_carry
    adder_1 ADDER (
      .a(a[i]),
      .b(b[i]),
      .c_in(carries[i]),
      .sum(sum[i]),
      .c_out(carries[i+1])
    );
  end
endgenerate

endmodule
// to instantiate
// adder_n #(.N(32)) adder_32bit_a ( port list );

01_game_of_life/neighbor_adder.sv
/* 
    an adder that we can daisy chain ripple carry adders
*/

module neighbor_adder(neighbors, living_neighbors);

    input logic [7:0] neighbors;
    output logic [3:0] living_neighbors;

    wire [2:0] sum1a, sum1b, sum1c, sum1d;
    wire [3:0] sum2a, sum2b;

    //adder gives us living_neighbors

    // 1 bit adders
    adder_n #(.N(1)) adder_1bit_a (
        .a(neighbors[0]), 
        .b(neighbors[1]), 
        .c_in(1'b0), 
        .sum(sum1a[0]), 
        .c_out(sum1a[1])
        );
    adder_n #(.N(1)) adder_1bit_b (
        .a(neighbors[2]), 
        .b(neighbors[3]), 
        .c_in(1'b0), 
        .sum(sum1b[0]), 
        .c_out(sum1b[1])
        );
    adder_n #(.N(1)) adder_1bit_c (
        .a(neighbors[4]), 
        .b(neighbors[5]), 
        .c_in(1'b0), 
        .sum(sum1c[0]), 
        .c_out(sum1c[1])
        );
    adder_n #(.N(1)) adder_1bit_d (
        .a(neighbors[6]), 
        .b(neighbors[7]), 
        .c_in(1'b0), 
        .sum(sum1d[0]), 
        .c_out(sum1d[1])
        );

    //2 bit adders
    adder_n #(.N(2)) adder_2bit_a (
        .a(sum1a), 
        .b(sum1b), 
        .c_in(1'b0), 
        .sum(sum2a[1:0]), 
        .c_out(sum2a[2])
        );
    adder_n #(.N(2)) adder_2bit_b (
        .a(sum1c), 
        .b(sum1d), 
        .c_in(1'b0), 
        .sum(sum2b[1:0]), 
        .c_out(sum2b[2])
        );

    //3 bit adder
    adder_n #(.N(3)) adder_3bit_a (
        .a(sum2a), 
        .b(sum2b), 
        .c_in(1'b0), 
        .sum(living_neighbors[2:0]), 
        .c_out(living_neighbors[3])
        );

endmodule

01_game_of_life/conway_cell.sv
`default_nettype none

module conway_cell(clk, rst, ena, state_0, state_d, state_q, neighbors);
  input wire clk;
  input wire rst;
  input wire ena;

  input wire state_0;
  output logic state_d;
  output logic state_q;

  input wire [7:0] neighbors;
  logic [3:0] living_neighbors;
  logic d1, d2;

  neighbor_adder UUT(neighbors, living_neighbors);
  
  always_ff @(posedge clk) begin : state_ff
    // if (rst) state_q <= 1'b0;
    // else if (ena) state_q <= state_d;
    if(rst) begin // create a mux
      state_q <= state_0;
    end
    else if (ena) begin
      state_q <= state_d;
    end
    else begin // This is not required, "default" else case
      state_q <= state_q; // hold current value
    end
  end

  always_comb begin : next_state
    d1 = (~state_q) & (~living_neighbors[3]) & (~living_neighbors[2]) & living_neighbors[1] & living_neighbors[0];
    d2 = state_q & (~living_neighbors[3]) & (~living_neighbors[2]) & living_neighbors[1];
    state_d = (d1 | d2); // & ena & (~rst); not needed since if statement in ff
  end

endmodule

01_game_of_life/test_conway_cell.sv
`timescale 1ns / 1ps
`default_nettype none

`define SIMULATION

module test_conway_cell;

  // logic [7:0] neighbors;
  // wire [3:0] living_neighbors;

  // neighbor_adder UUT(neighbors, living_neighbors);

  // initial begin
    
  //   $display("neighbors | living_neighbors");
  //   for (int i = 0; i < 16; i = i + 1) begin
  //     neighbors = i[7:0];
  //     #1 $display("%8b | %4b", neighbors, living_neighbors);
  //   end
        
  //   $finish;      
	// end

  logic clk, rst, ena, state_0;
  logic [7:0] neighbors;
  wire state_d, state_q;

  conway_cell UUT(
    .clk(clk), .rst(rst), .ena(ena),
    .neighbors(neighbors),
    .state_0(1'b0), .state_d(state_d), .state_q(state_q)
  );

  always #5 clk = ~clk; // Toggle a clock every 5 time units.
	

  /*
    Initial blocks are one of the few things in Verilog that actually
    executes sequentially like normal code, and runs at the top of a 
    simulation. This can sometimes work in synthesis... but it's much
    better practice to use proper synchronous reset logic instead!
  */
  initial begin
    // Initialize modules input.
    clk = 0;
    rst = 1; // Start reset in active state.
    ena = 1; // Not testing the ena function in this example (though you should try!)
    state_0 = 0;
    
    // Collect all internal variables for waveforms.
    $dumpfile("conway_cell.vcd");
    $dumpvars(0, UUT);
    
    // Wait at least one clock cycle before deasserting reset.
    repeat (2) @(posedge clk);
    rst = 0;
    
    $display("lrud : d : q");
    for (int i = 0; i < 255; i = i + 1) begin
      // Change inputs at a negative edge to avoid setup issues.
      @(negedge clk);
      neighbors = i[7:0];
      @(posedge clk);
      $display("%b : %b: %b", neighbors, state_d, state_q);
    end

    #10;
    $finish; // End the simulation.
	end

endmodule

01_game_of_life/conway_cell.vcd
$date
	Sun Oct 10 17:23:32 2021
$end
$version
	Icarus Verilog
$end
$timescale
	1ps
$end
$scope module test_conway_cell $end
$scope module UUT $end
$var wire 1 ! clk $end
$var wire 1 " ena $end
$var wire 8 # neighbors [7:0] $end
$var wire 1 $ rst $end
$var wire 1 % state_0 $end
$var wire 4 & living_neighbors [3:0] $end
$var reg 1 ' d1 $end
$var reg 1 ( d2 $end
$var reg 1 ) state_d $end
$var reg 1 * state_q $end
$scope module UUT $end
$var wire 8 + neighbors [7:0] $end
$var wire 4 , sum2b [3:0] $end
$var wire 4 - sum2a [3:0] $end
$var wire 3 . sum1d [2:0] $end
$var wire 3 / sum1c [2:0] $end
$var wire 3 0 sum1b [2:0] $end
$var wire 3 1 sum1a [2:0] $end
$var wire 4 2 living_neighbors [3:0] $end
$scope module adder_1bit_a $end
$var wire 1 3 a $end
$var wire 1 4 b $end
$var wire 1 5 c_in $end
$var wire 1 6 sum $end
$var wire 2 7 carries [1:0] $end
$var reg 1 8 c_out $end
$scope begin ripple_carry[0] $end
$scope module ADDER $end
$var wire 1 3 a $end
$var wire 1 4 b $end
$var wire 1 9 c_in $end
$var reg 1 : c_out $end
$var reg 1 6 sum $end
$scope begin adder_gates $end
$upscope $end
$upscope $end
$upscope $end
$upscope $end
$scope module adder_1bit_b $end
$var wire 1 ; a $end
$var wire 1 < b $end
$var wire 1 = c_in $end
$var wire 1 > sum $end
$var wire 2 ? carries [1:0] $end
$var reg 1 @ c_out $end
$scope begin ripple_carry[0] $end
$scope module ADDER $end
$var wire 1 ; a $end
$var wire 1 < b $end
$var wire 1 A c_in $end
$var reg 1 B c_out $end
$var reg 1 > sum $end
$scope begin adder_gates $end
$upscope $end
$upscope $end
$upscope $end
$upscope $end
$scope module adder_1bit_c $end
$var wire 1 C a $end
$var wire 1 D b $end
$var wire 1 E c_in $end
$var wire 1 F sum $end
$var wire 2 G carries [1:0] $end
$var reg 1 H c_out $end
$scope begin ripple_carry[0] $end
$scope module ADDER $end
$var wire 1 C a $end
$var wire 1 D b $end
$var wire 1 I c_in $end
$var reg 1 J c_out $end
$var reg 1 F sum $end
$scope begin adder_gates $end
$upscope $end
$upscope $end
$upscope $end
$upscope $end
$scope module adder_1bit_d $end
$var wire 1 K a $end
$var wire 1 L b $end
$var wire 1 M c_in $end
$var wire 1 N sum $end
$var wire 2 O carries [1:0] $end
$var reg 1 P c_out $end
$scope begin ripple_carry[0] $end
$scope module ADDER $end
$var wire 1 K a $end
$var wire 1 L b $end
$var wire 1 Q c_in $end
$var reg 1 R c_out $end
$var reg 1 N sum $end
$scope begin adder_gates $end
$upscope $end
$upscope $end
$upscope $end
$upscope $end
$scope module adder_2bit_a $end
$var wire 2 S a [1:0] $end
$var wire 2 T b [1:0] $end
$var wire 1 U c_in $end
$var wire 2 V sum [1:0] $end
$var wire 3 W carries [2:0] $end
$var reg 1 X c_out $end
$scope begin ripple_carry[0] $end
$scope module ADDER $end
$var wire 1 Y a $end
$var wire 1 Z b $end
$var wire 1 [ c_in $end
$var reg 1 \ c_out $end
$var reg 1 ] sum $end
$scope begin adder_gates $end
$upscope $end
$upscope $end
$upscope $end
$scope begin ripple_carry[1] $end
$scope module ADDER $end
$var wire 1 ^ a $end
$var wire 1 _ b $end
$var wire 1 ` c_in $end
$var reg 1 a c_out $end
$var reg 1 b sum $end
$scope begin adder_gates $end
$upscope $end
$upscope $end
$upscope $end
$upscope $end
$scope module adder_2bit_b $end
$var wire 2 c a [1:0] $end
$var wire 2 d b [1:0] $end
$var wire 1 e c_in $end
$var wire 2 f sum [1:0] $end
$var wire 3 g carries [2:0] $end
$var reg 1 h c_out $end
$scope begin ripple_carry[0] $end
$scope module ADDER $end
$var wire 1 i a $end
$var wire 1 j b $end
$var wire 1 k c_in $end
$var reg 1 l c_out $end
$var reg 1 m sum $end
$scope begin adder_gates $end
$upscope $end
$upscope $end
$upscope $end
$scope begin ripple_carry[1] $end
$scope module ADDER $end
$var wire 1 n a $end
$var wire 1 o b $end
$var wire 1 p c_in $end
$var reg 1 q c_out $end
$var reg 1 r sum $end
$scope begin adder_gates $end
$upscope $end
$upscope $end
$upscope $end
$upscope $end
$scope module adder_3bit_a $end
$var wire 3 s a [2:0] $end
$var wire 3 t b [2:0] $end
$var wire 1 u c_in $end
$var wire 3 v sum [2:0] $end
$var wire 4 w carries [3:0] $end
$var reg 1 x c_out $end
$scope begin ripple_carry[0] $end
$scope module ADDER $end
$var wire 1 y a $end
$var wire 1 z b $end
$var wire 1 { c_in $end
$var reg 1 | c_out $end
$var reg 1 } sum $end
$scope begin adder_gates $end
$upscope $end
$upscope $end
$upscope $end
$scope begin ripple_carry[1] $end
$scope module ADDER $end
$var wire 1 ~ a $end
$var wire 1 !" b $end
$var wire 1 "" c_in $end
$var reg 1 #" c_out $end
$var reg 1 $" sum $end
$scope begin adder_gates $end
$upscope $end
$upscope $end
$upscope $end
$scope begin ripple_carry[2] $end
$scope module ADDER $end
$var wire 1 %" a $end
$var wire 1 &" b $end
$var wire 1 '" c_in $end
$var reg 1 (" c_out $end
$var reg 1 )" sum $end
$scope begin adder_gates $end
$upscope $end
$upscope $end
$upscope $end
$upscope $end
$upscope $end
$scope begin next_state $end
$upscope $end
$scope begin state_ff $end
$upscope $end
$upscope $end
$upscope $end
$enddefinitions $end
#0
$dumpvars
x)"
x("
x'"
x&"
x%"
x$"
x#"
x""
x!"
x~
x}
x|
0{
xz
xy
xx
bx0 w
bx v
0u
bx t
bx s
xr
xq
xp
xo
xn
xm
xl
0k
xj
xi
xh
bx0 g
bx f
0e
bx d
bx c
xb
xa
x`
x_
x^
x]
x\
0[
xZ
xY
xX
bx0 W
bx V
0U
bx T
bx S
xR
0Q
xP
bx0 O
xN
0M
xL
xK
xJ
0I
xH
bx0 G
xF
0E
xD
xC
xB
0A
x@
bx0 ?
x>
0=
x<
x;
x:
09
x8
bx0 7
x6
05
x4
x3
bx 2
bzxx 1
bzxx 0
bzxx /
bzxx .
bzxxx -
bzxxx ,
bx +
x*
x)
x(
x'
bx &
0%
1$
bx #
1"
0!
$end
#5000
0(
0*
1!
#10000
0!
#15000
x(
x*
0$
1!
#20000
0)"
0)
0(
0'"
0$"
0#"
0~
0'
0""
0x
0!"
b0 &
b0 2
b0 v
0}
0|
b0 w
0("
0y
0%"
0b
0z
0&"
0r
b0 s
0`
0X
b0 t
0p
0h
bz000 -
b0 V
0]
0\
b0 W
0a
bz000 ,
b0 f
0m
0l
b0 g
0q
0Y
0^
0Z
0_
0i
0n
0j
0o
b0 S
08
b0 T
0@
b0 c
0H
b0 d
0P
bz00 1
06
b0 7
0:
bz00 0
0>
b0 ?
0B
bz00 /
0F
b0 G
0J
bz00 .
0N
b0 O
0R
03
04
0;
0<
0C
0D
0K
0L
b0 #
b0 +
0!
#25000
0*
1!
#30000
b1 &
b1 2
b1 v
1}
1y
b1 s
bz001 -
b1 V
1]
1Y
b1 S
bz01 1
16
13
b1 #
b1 +
0!
#35000
1!
#40000
03
14
b10 #
b10 +
0!
#45000
1!
#50000
0}
b10 &
b10 2
b10 v
1$"
0y
1~
b10 s
0]
bz010 -
b10 V
1b
0Y
1^
b10 S
18
bz10 1
06
b10 7
1:
13
b11 #
b11 +
0!
#55000
1!
#60000
0$"
0)
0'
0~
b1 &
b1 2
b1 v
1}
1y
0b
b1 s
0^
bz001 -
b1 V
1]
b0 S
1Z
bz00 1
08
b1 T
b0 7
0:
bz01 0
1>
03
04
1;
b100 #
b100 +
0!
#65000
1!
#70000
1$"
1~
b10 &
b10 2
b10 v
0}
0y
1b
b10 s
1`
bz010 -
b10 V
0]
b10 W
1\
1Y
b1 S
bz01 1
16
13
b101 #
b101 +
0!
#75000
1!
#80000
03
14
b110 #
b110 +
0!
#85000
1!
#90000
1)
1'
1}
1$"
b11 &
b11 2
b11 v
0)"
1y
1~
0%"
0`
b11 s
0X
1]
0\
bz011 -
b11 V
1b
b0 W
0a
0Y
1^
b10 S
18
bz10 1
06
b10 7
1:
13
b111 #
b111 +
0!
#95000
1(
0'
1*
1!
#100000
0)
0(
b1 &
b1 2
b1 v
0$"
0~
b1 s
bz001 -
b1 V
0b
0^
b0 S
bz00 1
08
b0 7
0:
03
04
0;
1<
b1000 #
b1000 +
0!
#105000
0*
1!
#110000
1$"
1~
b10 &
b10 2
b10 v
0}
0y
1b
b10 s
1`
bz010 -
b10 V
0]
b10 W
1\
1Y
b1 S
bz01 1
16
13
b1001 #
b1001 +
0!
#115000
1!
#120000
03
14
b1010 #
b1010 +
0!
#125000
1!
#130000
1)
1'
1}
1$"
b11 &
b11 2
b11 v
0)"
1y
1~
0%"
0`
b11 s
0X
1]
0\
bz011 -
b11 V
1b
b0 W
0a
0Y
1^
b10 S
18
bz10 1
06
b10 7
1:
13
b1011 #
b1011 +
0!
#135000
1(
0'
1*
1!
#140000
1)
1(
0}
1$"
b10 &
b10 2
b10 v
0)"
0y
1~
0%"
b10 s
0X
0^
0]
bz010 -
b10 V
1b
b0 W
0a
b0 S
0Z
1_
bz00 1
08
b10 T
1@
b0 7
0:
bz10 0
0>
b10 ?
1B
03
04
1;
b1100 #
b1100 +
0!
#145000
1!
#150000
b11 &
b11 2
b11 v
1}
1y
b11 s
bz011 -
b11 V
1]
1Y
b1 S
bz01 1
16
13
b1101 #
b1101 +
0!
#155000
1!
#160000
03
14
b1110 #
b1110 +
0!
#165000
1!
#170000
0)
0(
0}
0$"
b100 &
b100 2
b100 v
1)"
0y
0~
1%"
b100 s
1X
0]
bz100 -
b0 V
0b
b100 W
1a
0Y
1^
b10 S
18
bz10 1
06
b10 7
1:
13
b1111 #
b1111 +
0!
#175000
0*
1!
#180000
0)"
0%"
b0 s
b1 &
b1 2
b1 v
1}
bz000 -
0X
1z
b0 W
0a
b1 t
0^
0_
bz001 ,
b1 f
1m
b0 S
b0 T
1i
bz00 1
08
bz00 0
0@
b1 c
b0 7
0:
b0 ?
0B
bz01 /
1F
03
04
0;
0<
1C
b10000 #
b10000 +
0!
#185000
1!
#190000
1$"
1""
b10 &
b10 2
b10 v
0}
b10 w
1|
1y
b1 s
bz001 -
b1 V
1]
1Y
b1 S
bz01 1
16
13
b10001 #
b10001 +
0!
#195000
1!
#200000
03
14
b10010 #
b10010 +
0!
#205000
1!
#210000
1)
1'
0)"
0""
0'"
1}
0|
b11 &
b11 2
b11 v
1$"
b0 w
0#"
0y
1~
b10 s
0]
bz010 -
b10 V
1b
0Y
1^
b10 S
18
bz10 1
06
b10 7
1:
13
b10011 #
b10011 +
0!
#215000
1(
0'
1*
1!
#220000
1""
0~
b10 &
b10 2
b10 v
0}
b10 w
1|
1y
0b
b1 s
0^
bz001 -
b1 V
1]
b0 S
1Z
bz00 1
08
b1 T
b0 7
0:
bz01 0
1>
03
04
1;
b10100 #
b10100 +
0!
#225000
1!
#230000
0""
1~
b11 &
b11 2
b11 v
1}
b0 w
0|
0y
1b
b10 s
1`
bz010 -
b10 V
0]
b10 W
1\
1Y
b1 S
bz01 1
16
13
b10101 #
b10101 +
0!
#235000
1!
#240000
03
14
b10110 #
b10110 +
0!
#245000
1!
#250000
1'"
1#"
1""
0)
0(
0}
b110 w
1|
0$"
b100 &
b100 2
b100 v
1)"
1y
1~
0%"
0`
b11 s
0X
1]
0\
bz011 -
b11 V
1b
b0 W
0a
0Y
1^
b10 S
18
bz10 1
06
b10 7
1:
13
b10111 #
b10111 +
0!
#255000
0*
1!
#260000
0)"
0'"
b10 &
b10 2
b10 v
1$"
b10 w
0#"
0~
b1 s
bz001 -
b1 V
0b
0^
b0 S
bz00 1
08
b0 7
0:
03
04
0;
1<
b11000 #
b11000 +
0!
#265000
1!
#270000
1)
1'
0""
1~
b11 &
b11 2
b11 v
1}
b0 w
0|
0y
1b
b10 s
1`
bz010 -
b10 V
0]
b10 W
1\
1Y
b1 S
bz01 1
16
13
b11001 #
b11001 +
0!
#275000
1(
0'
1*
1!
#280000
03
14
b11010 #
b11010 +
0!
#285000
1!
#290000
1'"
1#"
1""
0)
0(
0}
b110 w
1|
0$"
b100 &
b100 2
b100 v
1)"
1y
1~
0%"
0`
b11 s
0X
1]
0\
bz011 -
b11 V
1b
b0 W
0a
0Y
1^
b10 S
18
bz10 1
06
b10 7
1:
13
b11011 #
b11011 +
0!
#295000
0*
1!
#300000
1)
1'
0""
0'"
0x
1}
0|
1$"
0#"
b11 &
b11 2
b11 v
0)"
b0 w
0("
0y
1~
0%"
b10 s
0X
0^
0]
bz010 -
b10 V
1b
b0 W
0a
b0 S
0Z
1_
bz00 1
08
b10 T
1@
b0 7
0:
bz10 0
0>
b10 ?
1B
03
04
1;
b11100 #
b11100 +
0!
#305000
1(
0'
1*
1!
#310000
1)"
0)
0(
1'"
0$"
1#"
1""
b100 &
b100 2
b100 v
0}
b110 w
1|
1y
b11 s
bz011 -
b11 V
1]
1Y
b1 S
bz01 1
16
13
b11101 #
b11101 +
0!
#315000
0*
1!
#320000
03
14
b11110 #
b11110 +
0!
#325000
1!
#330000
0""
0'"
0x
1}
0|
0$"
0#"
b101 &
b101 2
b101 v
1)"
b0 w
0("
0y
0~
1%"
b100 s
1X
0]
bz100 -
b0 V
0b
b100 W
1a
0Y
1^
b10 S
18
bz10 1
06
b10 7
1:
13
b11111 #
b11111 +
0!
#335000
1!
#340000
b1 &
b1 2
b1 v
0)"
0%"
b0 s
bz000 -
0X
b0 W
0a
0^
0_
b0 S
b0 T
bz00 1
08
bz00 0
0@
b0 7
0:
b0 ?
0B
03
04
0;
0<
0C
1D
b100000 #
b100000 +
0!
#345000
1!
#350000
1$"
1""
b10 &
b10 2
b10 v
0}
b10 w
1|
1y
b1 s
bz001 -
b1 V
1]
1Y
b1 S
bz01 1
16
13
b100001 #
b100001 +
0!
#355000
1!
#360000
03
14
b100010 #
b100010 +
0!
#365000
1!
#370000
1)
1'
0)"
0""
0'"
1}
0|
b11 &
b11 2
b11 v
1$"
b0 w
0#"
0y
1~
b10 s
0]
bz010 -
b10 V
1b
0Y
1^
b10 S
18
bz10 1
06
b10 7
1:
13
b100011 #
b100011 +
0!
#375000
1(
0'
1*
1!
#380000
1""
0~
b10 &
b10 2
b10 v
0}
b10 w
1|
1y
0b
b1 s
0^
bz001 -
b1 V
1]
b0 S
1Z
bz00 1
08
b1 T
b0 7
0:
bz01 0
1>
03
04
1;
b100100 #
b100100 +
0!
#385000
1!
#390000
0""
1~
b11 &
b11 2
b11 v
1}
b0 w
0|
0y
1b
b10 s
1`
bz010 -
b10 V
0]
b10 W
1\
1Y
b1 S
bz01 1
16
13
b100101 #
b100101 +
0!
#395000
1!
#400000
03
14
b100110 #
b100110 +
0!
#405000
1!
#410000
1'"
1#"
1""
0)
0(
0}
b110 w
1|
0$"
b100 &
b100 2
b100 v
1)"
1y
1~
0%"
0`
b11 s
0X
1]
0\
bz011 -
b11 V
1b
b0 W
0a
0Y
1^
b10 S
18
bz10 1
06
b10 7
1:
13
b100111 #
b100111 +
0!
#415000
0*
1!
#420000
0)"
0'"
b10 &
b10 2
b10 v
1$"
b10 w
0#"
0~
b1 s
bz001 -
b1 V
0b
0^
b0 S
bz00 1
08
b0 7
0:
03
04
0;
1<
b101000 #
b101000 +
0!
#425000
1!
#430000
1)
1'
0""
1~
b11 &
b11 2
b11 v
1}
b0 w
0|
0y
1b
b10 s
1`
bz010 -
b10 V
0]
b10 W
1\
1Y
b1 S
bz01 1
16
13
b101001 #
b101001 +
0!
#435000
1(
0'
1*
1!
#440000
03
14
b101010 #
b101010 +
0!
#445000
1!
#450000
1'"
1#"
1""
0)
0(
0}
b110 w
1|
0$"
b100 &
b100 2
b100 v
1)"
1y
1~
0%"
0`
b11 s
0X
1]
0\
bz011 -
b11 V
1b
b0 W
0a
0Y
1^
b10 S
18
bz10 1
06
b10 7
1:
13
b101011 #
b101011 +
0!
#455000
0*
1!
#460000
1)
1'
0""
0'"
0x
1}
0|
1$"
0#"
b11 &
b11 2
b11 v
0)"
b0 w
0("
0y
1~
0%"
b10 s
0X
0^
0]
bz010 -
b10 V
1b
b0 W
0a
b0 S
0Z
1_
bz00 1
08
b10 T
1@
b0 7
0:
bz10 0
0>
b10 ?
1B
03
04
1;
b101100 #
b101100 +
0!
#465000
1(
0'
1*
1!
#470000
1)"
0)
0(
1'"
0$"
1#"
1""
b100 &
b100 2
b100 v
0}
b110 w
1|
1y
b11 s
bz011 -
b11 V
1]
1Y
b1 S
bz01 1
16
13
b101101 #
b101101 +
0!
#475000
0*
1!
#480000
03
14
b101110 #
b101110 +
0!
#485000
1!
#490000
0""
0'"
0x
1}
0|
0$"
0#"
b101 &
b101 2
b101 v
1)"
b0 w
0("
0y
0~
1%"
b100 s
1X
0]
bz100 -
b0 V
0b
b100 W
1a
0Y
1^
b10 S
18
bz10 1
06
b10 7
1:
13
b101111 #
b101111 +
0!
#495000
1!
#500000
0)"
0%"
b0 s
0}
b10 &
b10 2
b10 v
1$"
bz000 -
0X
0z
1!"
b0 W
0a
b10 t
0^
0_
0m
bz010 ,
b10 f
1r
b0 S
b0 T
0i
1n
bz00 1
08
bz00 0
0@
b10 c
1H
b0 7
0:
b0 ?
0B
bz10 /
0F
b10 G
1J
03
04
0;
0<
1C
b110000 #
b110000 +
0!
#505000
1!
#510000
1)
1'
b11 &
b11 2
b11 v
1}
1y
b1 s
bz001 -
b1 V
1]
1Y
b1 S
bz01 1
16
13
b110001 #
b110001 +
0!
#515000
1(
0'
1*
1!
#520000
03
14
b110010 #
b110010 +
0!
#525000
1!
#530000
1)"
0)
0(
1'"
0}
b100 &
b100 2
b100 v
0$"
b100 w
1#"
0y
1~
b10 s
0]
bz010 -
b10 V
1b
0Y
1^
b10 S
18
bz10 1
06
b10 7
1:
13
b110011 #
b110011 +
0!
#535000
0*
1!
#540000
1)
1'
0)"
0'"
1$"
b0 w
0#"
0~
b11 &
b11 2
b11 v
1}
1y
0b
b1 s
0^
bz001 -
b1 V
1]
b0 S
1Z
bz00 1
08
b1 T
b0 7
0:
bz01 0
1>
03
04
1;
b110100 #
b110100 +
0!
#545000
1(
0'
1*
1!
#550000
1)"
0)
0(
1'"
0$"
b100 w
1#"
1~
b100 &
b100 2
b100 v
0}
0y
1b
b10 s
1`
bz010 -
b10 V
0]
b10 W
1\
1Y
b1 S
bz01 1
16
13
b110101 #
b110101 +
0!
#555000
0*
1!
#560000
03
14
b110110 #
b110110 +
0!
#565000
1!
#570000
1'"
0x
1}
0$"
1#"
b101 &
b101 2
b101 v
1)"
b100 w
0("
1y
1~
0%"
0`
b11 s
0X
1]
0\
bz011 -
b11 V
1b
b0 W
0a
0Y
1^
b10 S
18
bz10 1
06
b10 7
1:
13
b110111 #
b110111 +
0!
#575000
1!
#580000
1)
1'
0)"
0'"
b11 &
b11 2
b11 v
1$"
b0 w
0#"
0~
b1 s
bz001 -
b1 V
0b
0^
b0 S
bz00 1
08
b0 7
0:
03
04
0;
1<
b111000 #
b111000 +
0!
#585000
1(
0'
1*
1!
#590000
1)"
0)
0(
1'"
0$"
b100 w
1#"
1~
b100 &
b100 2
b100 v
0}
0y
1b
b10 s
1`
bz010 -
b10 V
0]
b10 W
1\
1Y
b1 S
bz01 1
16
13
b111001 #
b111001 +
0!
#595000
0*
1!
#600000
03
14
b111010 #
b111010 +
0!
#605000
1!
#610000
1'"
0x
1}
0$"
1#"
b101 &
b101 2
b101 v
1)"
b100 w
0("
1y
1~
0%"
0`
b11 s
0X
1]
0\
bz011 -
b11 V
1b
b0 W
0a
0Y
1^
b10 S
18
bz10 1
06
b10 7
1:
13
b111011 #
b111011 +
0!
#615000
1!
#620000
1'"
0x
0}
0$"
1#"
b100 &
b100 2
b100 v
1)"
b100 w
0("
0y
1~
0%"
b10 s
0X
0^
0]
bz010 -
b10 V
1b
b0 W
0a
b0 S
0Z
1_
bz00 1
08
b10 T
1@
b0 7
0:
bz10 0
0>
b10 ?
1B
03
04
1;
b111100 #
b111100 +
0!
#625000
1!
#630000
b101 &
b101 2
b101 v
1}
1y
b11 s
bz011 -
b11 V
1]
1Y
b1 S
bz01 1
16
13
b111101 #
b111101 +
0!
#635000
1!
#640000
03
14
b111110 #
b111110 +
0!
#645000
1!
#650000
0'"
0x
0}
1$"
0#"
b110 &
b110 2
b110 v
1)"
b0 w
0("
0y
0~
1%"
b100 s
1X
0]
bz100 -
b0 V
0b
b100 W
1a
0Y
1^
b10 S
18
bz10 1
06
b10 7
1:
13
b111111 #
b111111 +
0!
#655000
1!
#660000
0)"
0%"
0$"
b0 s
0!"
b1 &
b1 2
b1 v
1}
bz000 -
0X
1z
b0 W
0a
0r
b1 t
0^
0_
0n
bz001 ,
b1 f
1m
b0 S
b0 T
b0 c
1j
bz00 1
08
bz00 0
0@
bz00 /
0H
b1 d
b0 7
0:
b0 ?
0B
b0 G
0J
bz01 .
1N
03
04
0;
0<
0C
0D
1K
b1000000 #
b1000000 +
0!
#665000
1!
#670000
1$"
1""
b10 &
b10 2
b10 v
0}
b10 w
1|
1y
b1 s
bz001 -
b1 V
1]
1Y
b1 S
bz01 1
16
13
b1000001 #
b1000001 +
0!
#675000
1!
#680000
03
14
b1000010 #
b1000010 +
0!
#685000
1!
#690000
1)
1'
0)"
0""
0'"
1}
0|
b11 &
b11 2
b11 v
1$"
b0 w
0#"
0y
1~
b10 s
0]
bz010 -
b10 V
1b
0Y
1^
b10 S
18
bz10 1
06
b10 7
1:
13
b1000011 #
b1000011 +
0!
#695000
1(
0'
1*
1!
#700000
1""
0~
b10 &
b10 2
b10 v
0}
b10 w
1|
1y
0b
b1 s
0^
bz001 -
b1 V
1]
b0 S
1Z
bz00 1
08
b1 T
b0 7
0:
bz01 0
1>
03
04
1;
b1000100 #
b1000100 +
0!
#705000
1!
#710000
0""
1~
b11 &
b11 2
b11 v
1}
b0 w
0|
0y
1b
b10 s
1`
bz010 -
b10 V
0]
b10 W
1\
1Y
b1 S
bz01 1
16
13
b1000101 #
b1000101 +
0!
#715000
1!
#720000
03
14
b1000110 #
b1000110 +
0!
#725000
1!
#730000
1'"
1#"
1""
0)
0(
0}
b110 w
1|
0$"
b100 &
b100 2
b100 v
1)"
1y
1~
0%"
0`
b11 s
0X
1]
0\
bz011 -
b11 V
1b
b0 W
0a
0Y
1^
b10 S
18
bz10 1
06
b10 7
1:
13
b1000111 #
b1000111 +
0!
#735000
0*
1!
#740000
0)"
0'"
b10 &
b10 2
b10 v
1$"
b10 w
0#"
0~
b1 s
bz001 -
b1 V
0b
0^
b0 S
bz00 1
08
b0 7
0:
03
04
0;
1<
b1001000 #
b1001000 +
0!
#745000
1!
#750000
1)
1'
0""
1~
b11 &
b11 2
b11 v
1}
b0 w
0|
0y
1b
b10 s
1`
bz010 -
b10 V
0]
b10 W
1\
1Y
b1 S
bz01 1
16
13
b1001001 #
b1001001 +
0!
#755000
1(
0'
1*
1!
#760000
03
14
b1001010 #
b1001010 +
0!
#765000
1!
#770000
1'"
1#"
1""
0)
0(
0}
b110 w
1|
0$"
b100 &
b100 2
b100 v
1)"
1y
1~
0%"
0`
b11 s
0X
1]
0\
bz011 -
b11 V
1b
b0 W
0a
0Y
1^
b10 S
18
bz10 1
06
b10 7
1:
13
b1001011 #
b1001011 +
0!
#775000
0*
1!
#780000
1)
1'
0""
0'"
0x
1}
0|
1$"
0#"
b11 &
b11 2
b11 v
0)"
b0 w
0("
0y
1~
0%"
b10 s
0X
0^
0]
bz010 -
b10 V
1b
b0 W
0a
b0 S
0Z
1_
bz00 1
08
b10 T
1@
b0 7
0:
bz10 0
0>
b10 ?
1B
03
04
1;
b1001100 #
b1001100 +
0!
#785000
1(
0'
1*
1!
#790000
1)"
0)
0(
1'"
0$"
1#"
1""
b100 &
b100 2
b100 v
0}
b110 w
1|
1y
b11 s
bz011 -
b11 V
1]
1Y
b1 S
bz01 1
16
13
b1001101 #
b1001101 +
0!
#795000
0*
1!
#800000
03
14
b1001110 #
b1001110 +
0!
#805000
1!
#810000
0""
0'"
0x
1}
0|
0$"
0#"
b101 &
b101 2
b101 v
1)"
b0 w
0("
0y
0~
1%"
b100 s
1X
0]
bz100 -
b0 V
0b
b100 W
1a
0Y
1^
b10 S
18
bz10 1
06
b10 7
1:
13
b1001111 #
b1001111 +
0!
#815000
1!
